Workbook

Sheet Alyssa Screening
A1: Address
B3: Purchase Price | C3: 1275000 | E3: Taxes | F3: 15000 | H3: Vacancy | I3: 0.05 | K3: Sqft | L3: 0
B4: % Down | C4: 0.25 | E4: Insurance | F4: 2500 | K4: Price/Sqft | L4: =C3/L3 -> #DIV/0!
B5: Equity Down | C5: =C3*C4 -> 318750 | K5: GRM | L5: =C3/C15 -> 12.957317
E6: Water | F6: 0
B7: Unit 1 | C7: 2050 | E7: Electricity | F7: 0
B8: Unit 2 | C8: 2050 | E8: Garbage | F8: 0
B9: Unit 3 | C9: 2050 | E9: Lawn | F9: 0
B10: Unit 4 | C10: 2050 | E10: Handyman | F10: 0
B11: Unit 5 | C11: 0 | E11: Other | F11: 0
B12: Unit 6 | C12: 0 | E12: Vacancy | F12: =SUM(C7:C12)*I3*12 -> 4920
E13: OpEx | F13: =SUM(F6:F12) -> 4920
B14: Monthly Rent Income | C14: =SUM(C7:C12) -> 8200
B15: Annual Rent Income | C15: =C14*12 -> 98400 | E15: Monthly Expense | F15: =F16/12 -> 1868.3333
E16: Annual Expense | F16: =F3+F4+F13 -> 22420
B17: Monthly NOI | C17: =C14-F15 -> 6331.6667
B18: Annual NOI | C18: =C15-F16 -> 75980
B19: Cap Rate | C19: =C18/C3 -> 0.059592157
B21: Monthly Mtge. Pmt. | C21: ='Mortgage and Ammortization'!B6 -> 6202.2193
B22: Annual Mtge. Pmt. | C22: =C21*12 -> 74426.632
B24: Monthly Cash Flow | C24: =C17-C21 -> 129.44737
B25: Annual Cash Flow | C25: =C18-C22 -> 1553.3684
B26: CoC Return | C26: =C25/C5 -> 0.0048733127
B27: DSCR | C27: =C18/C22 -> 1.0208711

Sheet Sources
B2: Source | C2: Balance | D2: PnL | E2: Tax | F2: Net Avail
B3: Jack 401k | C3: 50000
B4: Alyssa 401k | C4: 50000
B5: Jack Etrade Cash | C5: 400000
B6: Jack Etrade Stock | C6: 561836 | D6: 138713 | E6: =D6*20% -> 27742.6 | F6: =C6-E6 -> 534093.4
B7: Alyssa Robinhood | C7: 90000 | D7: 36000 | E7: =D7*20% -> 7200 | F7: =C7-E7 -> 82800
B9: Cash Avail | C9: =C3+C4+C5 -> 500000
B10: Stock Buffer | C10: 250000
B11: Stock Avail | C11: =F6-C10 -> 284093.4
B12: Bonus | C12: 0
B13: Total Avail | C13: =C9+C11+C12 -> 784093.4
B14: Down Payment | C14: 0.25
B15: Sticker Price | C15: =C13/C14 -> 3136373.6

Sheet Mortgage and Ammortization
A1: Purchase Price | B1: ='Alyssa Screening'!C3 -> 1275000
A2: Equity | B2: ='Alyssa Screening'!C5 -> 318750
A3: Loan Size | B3: =B1-B2 -> 956250
A4: Mortgage Rate | B4: 0.0675 | D4: Period | F4: Principal Pay | G4: Interest Pay | H4: Total Payment | I4: Principal Outstanding | K4: Running Principal Paid | L4: Running Interest Paid | M4: Running Total Payment
A5: Term | B5: 360 | D5: 0 | E5: =EOMONTH(TODAY(),1) -> 46081 | I5: =$B$3 -> 956250
A6: Monthly Mortgage Payment | B6: =PMT((B4/12),B5,-B3,0) -> 6202.2193 | D6: 1 | E6: =EOMONTH(E5,1) -> 46112 | F6: =PPMT($B$4/12,D6,$B$5,-$B$3,0) -> 823.31305 | G6: =H6-F6 -> 5378.9063 | H6: =$B$6 -> 6202.2193 | I6: =I5-F6 -> 955426.69 | K6: =F6 -> 823.31305 | L6: =G6 -> 5378.9063 | M6: =H6 -> 6202.2193
A7: Annual Mortgage Payment | B7: =B6*12 -> 74426.632 | D7: =D6+1 -> 2 | E7: =EOMONTH(E6,1) -> 46142 | F7: =PPMT($B$4/12,D7,$B$5,-$B$3,0) -> 827.94418 | G7: =H7-F7 -> 5374.2751 | H7: =$B$6 -> 6202.2193 | I7: =I6-F7 -> 954598.74 | K7: =K6+F7 -> 1651.2572 | L7: =L6+G7 -> 10753.181 | M7: =M6+H7 -> 12404.439
D8: =D7+1 -> 3 | E8: =EOMONTH(E7,1) -> 46173 | F8: =PPMT($B$4/12,D8,$B$5,-$B$3,0) -> 832.60137 | G8: =H8-F8 -> 5369.6179 | H8: =$B$6 -> 6202.2193 | I8: =I7-F8 -> 953766.14 | K8: =K7+F8 -> 2483.8586 | L8: =L7+G8 -> 16122.799 | M8: =M7+H8 -> 18606.658
D9: =D8+1 -> 4 | E9: =EOMONTH(E8,1) -> 46203 | F9: =PPMT($B$4/12,D9,$B$5,-$B$3,0) -> 837.28475 | G9: =H9-F9 -> 5364.9345 | H9: =$B$6 -> 6202.2193 | I9: =I8-F9 -> 952928.86 | K9: =K8+F9 -> 3321.1434 | L9: =L8+G9 -> 21487.734 | M9: =M8+H9 -> 24808.877
D10: =D9+1 -> 5 | E10: =EOMONTH(E9,1) -> 46234 | F10: =PPMT($B$4/12,D10,$B$5,-$B$3,0) -> 841.99448 | G10: =H10-F10 -> 5360.2248 | H10: =$B$6 -> 6202.2193 | I10: =I9-F10 -> 952086.86 | K10: =K9+F10 -> 4163.1378 | L10: =L9+G10 -> 26847.959 | M10: =M9+H10 -> 31011.096
D11: =D10+1 -> 6 | E11: =EOMONTH(E10,1) -> 46265 | F11: =PPMT($B$4/12,D11,$B$5,-$B$3,0) -> 846.7307 | G11: =H11-F11 -> 5355.4886 | H11: =$B$6 -> 6202.2193 | I11: =I10-F11 -> 951240.13 | K11: =K10+F11 -> 5009.8685 | L11: =L10+G11 -> 32203.447 | M11: =M10+H11 -> 37213.316
D12: =D11+1 -> 7 | E12: =EOMONTH(E11,1) -> 46295 | F12: =PPMT($B$4/12,D12,$B$5,-$B$3,0) -> 851.49356 | G12: =H12-F12 -> 5350.7257 | H12: =$B$6 -> 6202.2193 | I12: =I11-F12 -> 950388.64 | K12: =K11+F12 -> 5861.3621 | L12: =L11+G12 -> 37554.173 | M12: =M11+H12 -> 43415.535
D13: =D12+1 -> 8 | E13: =EOMONTH(E12,1) -> 46326 | F13: =PPMT($B$4/12,D13,$B$5,-$B$3,0) -> 856.28321 | G13: =H13-F13 -> 5345.9361 | H13: =$B$6 -> 6202.2193 | I13: =I12-F13 -> 949532.35 | K13: =K12+F13 -> 6717.6453 | L13: =L12+G13 -> 42900.109 | M13: =M12+H13 -> 49617.754
D14: =D13+1 -> 9 | E14: =EOMONTH(E13,1) -> 46356 | F14: =PPMT($B$4/12,D14,$B$5,-$B$3,0) -> 861.0998 | G14: =H14-F14 -> 5341.1195 | H14: =$B$6 -> 6202.2193 | I14: =I13-F14 -> 948671.25 | K14: =K13+F14 -> 7578.7451 | L14: =L13+G14 -> 48241.229 | M14: =M13+H14 -> 55819.974
D15: =D14+1 -> 10 | E15: =EOMONTH(E14,1) -> 46387 | F15: =PPMT($B$4/12,D15,$B$5,-$B$3,0) -> 865.94349 | G15: =H15-F15 -> 5336.2758 | H15: =$B$6 -> 6202.2193 | I15: =I14-F15 -> 947805.31 | K15: =K14+F15 -> 8444.6886 | L15: =L14+G15 -> 53577.504 | M15: =M14+H15 -> 62022.193
D16: =D15+1 -> 11 | E16: =EOMONTH(E15,1) -> 46418 | F16: =PPMT($B$4/12,D16,$B$5,-$B$3,0) -> 870.81442 | G16: =H16-F16 -> 5331.4049 | H16: =$B$6 -> 6202.2193 | I16: =I15-F16 -> 946934.5 | K16: =K15+F16 -> 9315.503 | L16: =L15+G16 -> 58908.909 | M16: =M15+H16 -> 68224.412
D17: =D16+1 -> 12 | E17: =EOMONTH(E16,1) -> 46446 | F17: =PPMT($B$4/12,D17,$B$5,-$B$3,0) -> 875.71275 | G17: =H17-F17 -> 5326.5065 | H17: =$B$6 -> 6202.2193 | I17: =I16-F17 -> 946058.78 | K17: =K16+F17 -> 10191.216 | L17: =L16+G17 -> 64235.416 | M17: =M16+H17 -> 74426.632
D18: =D17+1 -> 13 | E18: =EOMONTH(E17,1) -> 46477 | F18: =PPMT($B$4/12,D18,$B$5,-$B$3,0) -> 880.63864 | G18: =H18-F18 -> 5321.5807 | H18: =$B$6 -> 6202.2193 | I18: =I17-F18 -> 945178.15 | K18: =K17+F18 -> 11071.854 | L18: =L17+G18 -> 69556.996 | M18: =M17+H18 -> 80628.851
D19: =D18+1 -> 14 | E19: =EOMONTH(E18,1) -> 46507 | F19: =PPMT($B$4/12,D19,$B$5,-$B$3,0) -> 885.59223 | G19: =H19-F19 -> 5316.6271 | H19: =$B$6 -> 6202.2193 | I19: =I18-F19 -> 944292.55 | K19: =K18+F19 -> 11957.447 | L19: =L18+G19 -> 74873.624 | M19: =M18+H19 -> 86831.07
... D365: =D364+1 -> 360 | E365: =EOMONTH(E364,1) -> 57039 | F365: =PPMT($B$4/12,D365,$B$5,-$B$3,0) -> 6167.527 | G365: =H365-F365 -> 34.692339 | H365: =$B$6 -> 6202.2193 | I365: =I364-F365 -> -4.2746251e-11 | K365: =K364+F365 -> 956250 | L365: =L364+G365 -> 1276548.9 | M365: =M364+H365 -> 2232798.9

Sheet Deal Screen Template
B1: Checklist Item | C1: Total | E1: Unit 1 | F1: Unit 2 | G1: Unit 3 | H1: Unit 4 | I1: Unit 5 | J1: Unit 6 | L1: Address
B2: Purchase Price | L2: Link
B3: % Down | C3: 0.25 | L3: Neighborhood
B4: Equity Down | C4: =C2*C3 -> 0 | L4: Structural Soundness?
A5: =SUM(E5:J5)/SUM(E5:J5) -> #DIV/0! | B5: Gross Monthly Rent | C5: =SUM(E5:J5)*A5 -> #DIV/0! | L5: Benefit from Cosmetics?
B6: Annual Gross Rent | C6: =C5*12 -> #DIV/0! | L6: Differentiating Features
B7: Number of Units | C7: =COUNT(E5:J5) -> 0 | L7: Date Posted
B8: Bedrooms | C8: =SUM(E8:J8) -> 0 | L8: Baths
B9: GRM | C9: =C2/(C5*12) -> #DIV/0! | L9: Home SqFt
B10: First Lease Expiry | C10: =MIN(E10:J10) -> 0 | L10: Lot Size
B11: Current Annual Taxes
B12: Expected Annual Taxes
B13: Expected Monthly Taxes | C13: =C12/12 -> 0
B14: Expected Annual Insurance Cost
B15: Expected Monthly Insurance Cost | C15: =C14/12 -> 0
B16: Expected Annual Maintenance Costs | C16: =C17*12 -> 0
B17: Expected Monthly Maintence Costs | C17: =SUM(C18:C20) -> 0
B18: Water
B19: Pest
B20: Lawn
B21: Annual Utility Costs Not Covered by Tenant | C21: 0
B22: Monthly Utility Costs Not Covered by Tenant | C22: =C21/12 -> 0
B23: Needed Repairs/Improvements Cost | C23: 0
B24: Monthly NOI | C24: =C5+C13+C15+C17+C22+(C23/12) -> #DIV/0!
B25: Monthly Mortgage Payment | C25: =-'Mortgage and Ammortization'!B6 -> -6202.2193
B27: Monthly Cash Flow | C27: =C24+C25 -> #DIV/0!
B29: Annual NOI | C29: =C24*12 -> #DIV/0!
B30: Annual Mortgage Payment | C30: =C25*12 -> -74426.632
B32: Annual Cash Flow | C32: =C29+C30 -> #DIV/0!
B34: Cap Rate | C34: =C29/C2 -> #DIV/0!
B35: DSCR | C35: =C29/-C30 -> #DIV/0!
B36: Cash on Cash Return | C36: =C32/C4 -> #DIV/0!
B37: 1y Total Return | C37: ='Total Returns'!B17 -> #DIV/0!
B39: Total Equity PP | C39: =C4/4 -> 0
B40: Donald Cap | C40: 50000
B41: JJ/BD/JG Equity | C41: =(C4-C40)/3 -> -16666.667

Sheet Total Returns
E1: Period | F1: 0 | G1: =F1+1 -> 1 | H1: =G1+1 -> 2 | I1: =H1+1 -> 3 | J1: =I1+1 -> 4 | K1: =J1+1 -> 5 | L1: =K1+1 -> 6 | M1: =L1+1 -> 7 | N1: =M1+1 -> 8 | ... DV1: =DU1+1 -> 120
E2: Date | F2: ='Mortgage and Ammortization'!$E$5 -> 46081 | G2: =EOMONTH(F2,1) -> 46112 | H2: =EOMONTH(G2,1) -> 46142 | I2: =EOMONTH(H2,1) -> 46173 | J2: =EOMONTH(I2,1) -> 46203 | K2: =EOMONTH(J2,1) -> 46234 | L2: =EOMONTH(K2,1) -> 46265 | M2: =EOMONTH(L2,1) -> 46295 | N2: =EOMONTH(M2,1) -> 46326 | ... DV2: =EOMONTH(DU2,1) -> 49734
A4: Appreciation Assumption | B4: 0 | E4: Home Value | F4: ='Deal Screen Template'!$C$2 -> 0 | G4: =F4*(1+($B$4/12)) -> 0 | H4: =G4*(1+($B$4/12)) -> 0 | I4: =H4*(1+($B$4/12)) -> 0 | J4: =I4*(1+($B$4/12)) -> 0 | K4: =J4*(1+($B$4/12)) -> 0 | L4: =K4*(1+($B$4/12)) -> 0 | M4: =L4*(1+($B$4/12)) -> 0 | N4: =M4*(1+($B$4/12)) -> 0 | ... DV4: =DU4*(1+($B$4/12)) -> 0
A5: Rent Increase Assumption | B5: 0 | E5: Debt Outstanding | F5: =VLOOKUP(F1,'Mortgage and Ammortization'!$D:$I,6,FALSE) -> 956250 | G5: =VLOOKUP(G1,'Mortgage and Ammortization'!$D:$I,6,FALSE) -> 955426.69 | H5: =VLOOKUP(H1,'Mortgage and Ammortization'!$D:$I,6,FALSE) -> 954598.74 | I5: =VLOOKUP(I1,'Mortgage and Ammortization'!$D:$I,6,FALSE) -> 953766.14 | J5: =VLOOKUP(J1,'Mortgage and Ammortization'!$D:$I,6,FALSE) -> 952928.86 | K5: =VLOOKUP(K1,'Mortgage and Ammortization'!$D:$I,6,FALSE) -> 952086.86 | L5: =VLOOKUP(L1,'Mortgage and Ammortization'!$D:$I,6,FALSE) -> 951240.13 | M5: =VLOOKUP(M1,'Mortgage and Ammortization'!$D:$I,6,FALSE) -> 950388.64 | ... DV5: =VLOOKUP(DV1,'Mortgage and Ammortization'!$D:$I,6,FALSE) -> 815690.8
A6: Refi Down Payment | B6: 0.25 | E6: Home Equity | F6: =F4-F5 -> -956250 | G6: =G4-G5 -> -955426.69 | H6: =H4-H5 -> -954598.74 | I6: =I4-I5 -> -953766.14 | J6: =J4-J5 -> -952928.86 | K6: =K4-K5 -> -952086.86 | L6: =L4-L5 -> -951240.13 | M6: =M4-M5 -> -950388.64 | ... DV6: =DV4-DV5 -> -815690.8
E8: Rental Cash Flow | F8: 0 | G8: ='Deal Screen Template'!$C$27 -> #DIV/0! | H8: =G8*(1+($B$5/12)) -> #DIV/0! | I8: =H8*(1+($B$5/12)) -> #DIV/0! | J8: =I8*(1+($B$5/12)) -> #DIV/0! | K8: =J8*(1+($B$5/12)) -> #DIV/0! | L8: =K8*(1+($B$5/12)) -> #DIV/0! | M8: =L8*(1+($B$5/12)) -> #DIV/0! | N8: =M8*(1+($B$5/12)) -> #DIV/0! | O8: =N8*(1+($B$5/12)) -> #DIV/0! | ... DV8: =DU8*(1+($B$5/12)) -> #DIV/0!
E9: Principal Paydown | F9: =VLOOKUP(F1,'Mortgage and Ammortization'!$D:$F,3,FALSE) -> 0 | G9: =VLOOKUP(G1,'Mortgage and Ammortization'!$D:$F,3,FALSE) -> 823.31305 | H9: =VLOOKUP(H1,'Mortgage and Ammortization'!$D:$F,3,FALSE) -> 827.94418 | I9: =VLOOKUP(I1,'Mortgage and Ammortization'!$D:$F,3,FALSE) -> 832.60137 | J9: =VLOOKUP(J1,'Mortgage and Ammortization'!$D:$F,3,FALSE) -> 837.28475 | K9: =VLOOKUP(K1,'Mortgage and Ammortization'!$D:$F,3,FALSE) -> 841.99448 | L9: =VLOOKUP(L1,'Mortgage and Ammortization'!$D:$F,3,FALSE) -> 846.7307 | M9: =VLOOKUP(M1,'Mortgage and Ammortization'!$D:$F,3,FALSE) -> 851.49356 | ... DV9: =VLOOKUP(DV1,'Mortgage and Ammortization'!$D:$F,3,FALSE) -> 1604.9308
E10: 200k | F10: 200000 | G10: 200000 | H10: 200000 | I10: 200000 | J10: 200000 | K10: 200000 | L10: 200000 | M10: 200000 | N10: 200000 | O10: 200000 | P10: 200000 | Q10: 200000 | R10: 200000 | S10: 200000 | T10: 200000 | U10: 200000 | V10: 200000 | W10: 200000 | X10: 200000 | Y10: 200000 | Z10: 200000 | AA10: 200000 | AB10: 200000 | AC10: 200000 | AD10: 200000 | AE10: 200000 | AF10: 200000 | AG10: 200000 | AH10: 200000 | AI10: 200000 | AJ10: 200000 | AK10: 200000 | AL10: 200000 | AM10: 200000 | AN10: 200000 | AO10: 200000 | AP10: 200000 | AQ10: 200000 | AR10: 200000 | AS10: 200000 | AT10: 200000 | AU10: 200000 | AV10: 200000 | AW10: 200000 | AX10: 200000 | AY10: 200000 | AZ10: 200000 | BA10: 200000 | BB10: 200000 | BC10: 200000 | BD10: 200000 | BE10: 200000 | BF10: 200000 | BG10: 200000 | BH10: 200000 | BI10: 200000 | BJ10: 200000 | BK10: 200000 | BL10: 200000 | BM10: 200000 | BN10: 200000 | BO10: 200000 | BP10: 200000 | BQ10: 200000 | BR10: 200000 | BS10: 200000 | BT10: 200000 | BU10: 200000 | BV10: 200000 | BW10: 200000 | BX10: 200000 | BY10: 200000 | BZ10: 200000 | CA10: 200000 | CB10: 200000 | CC10: 200000 | CD10: 200000 | CE10: 200000 | CF10: 200000 | CG10: 200000 | CH10: 200000 | CI10: 200000 | CJ10: 200000 | CK10: 200000 | CL10: 200000 | CM10: 200000 | CN10: 200000 | CO10: 200000 | CP10: 200000 | CQ10: 200000 | CR10: 200000 | CS10: 200000 | CT10: 200000 | CU10: 200000 | CV10: 200000 | CW10: 200000 | CX10: 200000 | CY10: 200000 | CZ10: 200000 | DA10: 200000 | DB10: 200000 | DC10: 200000 | DD10: 200000 | DE10: 200000 | DF10: 200000 | DG10: 200000 | DH10: 200000 | DI10: 200000 | DJ10: 200000 | DK10: 200000 | DL10: 200000 | DM10: 200000 | DN10: 200000 | DO10: 200000 | DP10: 200000 | DQ10: 200000 | DR10: 200000 | DS10: 200000 | DT10: 200000 | DU10: 200000 | DV10: 200000
A11: 1y IRR | B11: =XIRR(F19:R19,F2:R2) -> #DIV/0! | E11: Refi Available | F11: =(F4*(1-$B$6))-F5 -> -956250 | G11: =(G4*(1-$B$6))-G5 -> -955426.69 | H11: =(H4*(1-$B$6))-H5 -> -954598.74 | I11: =(I4*(1-$B$6))-I5 -> -953766.14 | J11: =(J4*(1-$B$6))-J5 -> -952928.86 | K11: =(K4*(1-$B$6))-K5 -> -952086.86 | L11: =(L4*(1-$B$6))-L5 -> -951240.13 | M11: =(M4*(1-$B$6))-M5 -> -950388.64 | ... DV11: =(DV4*(1-$B$6))-DV5 -> -815690.8
A12: 3y IRR | B12: =XIRR(F20:AP20,F2:AP2) -> #DIV/0!
A13: 5y IRR | B13: =XIRR(F21:BN21,F2:BN2) -> #DIV/0! | E13: Total Return | F13: =((F6+SUM($F$8:F8))/$F$6)-1 -> 0 | G13: =((G6+SUM($F$8:G8))/$F$6)-1 -> #DIV/0! | H13: =((H6+SUM($F$8:H8))/$F$6)-1 -> #DIV/0! | I13: =((I6+SUM($F$8:I8))/$F$6)-1 -> #DIV/0! | J13: =((J6+SUM($F$8:J8))/$F$6)-1 -> #DIV/0! | K13: =((K6+SUM($F$8:K8))/$F$6)-1 -> #DIV/0! | L13: =((L6+SUM($F$8:L8))/$F$6)-1 -> #DIV/0! | M13: =((M6+SUM($F$8:M8))/$F$6)-1 -> #DIV/0! | ... DV13: =((DV6+SUM($F$8:DV8))/$F$6)-1 -> #DIV/0!
A14: 7y IRR | B14: =XIRR(F22:CL22,F2:CL2) -> #DIV/0! | E14: Rolling Annualized | F14: 0 | G14: =(1+G13)^(12/G1)-1 -> #DIV/0! | H14: =(1+H13)^(12/H1)-1 -> #DIV/0! | I14: =(1+I13)^(12/I1)-1 -> #DIV/0! | J14: =(1+J13)^(12/J1)-1 -> #DIV/0! | K14: =(1+K13)^(12/K1)-1 -> #DIV/0! | L14: =(1+L13)^(12/L1)-1 -> #DIV/0! | M14: =(1+M13)^(12/M1)-1 -> #DIV/0! | N14: =(1+N13)^(12/N1)-1 -> #DIV/0! | ... DV14: =(1+DV13)^(12/DV1)-1 -> #DIV/0!
A15: 10y IRR | B15: =XIRR(F23:DV23,F2:DV2) -> #DIV/0! | E15: Accumulated Cash | F15: =SUM($F$8:F8) -> 0 | G15: =SUM($F$8:G8) -> #DIV/0! | H15: =SUM($F$8:H8) -> #DIV/0! | I15: =SUM($F$8:I8) -> #DIV/0! | J15: =SUM($F$8:J8) -> #DIV/0! | K15: =SUM($F$8:K8) -> #DIV/0! | L15: =SUM($F$8:L8) -> #DIV/0! | M15: =SUM($F$8:M8) -> #DIV/0! | ... DV15: =SUM($F$8:DV8) -> #DIV/0!
E16: Refi + Accum Cash | F16: =F11+F15 -> -956250 | G16: =G11+G15 -> #DIV/0! | H16: =H11+H15 -> #DIV/0! | I16: =I11+I15 -> #DIV/0! | J16: =J11+J15 -> #DIV/0! | K16: =K11+K15 -> #DIV/0! | L16: =L11+L15 -> #DIV/0! | M16: =M11+M15 -> #DIV/0! | ... DV16: =DV11+DV15 -> #DIV/0!
A17: 1y Total Return | B17: =R13 -> #DIV/0!
D19: 12 | E19: 1y IRR Stream | F19: =-$F$6 -> 956250 | G19: =IF(G$1<=$D19,IF(G$1=$D19,G$8+G$11,G$8),"") -> #DIV/0! | H19: =IF(H$1<=$D19,IF(H$1=$D19,H$8+H$11,H$8),"") -> #DIV/0! | I19: =IF(I$1<=$D19,IF(I$1=$D19,I$8+I$11,I$8),"") -> #DIV/0! | J19: =IF(J$1<=$D19,IF(J$1=$D19,J$8+J$11,J$8),"") -> #DIV/0! | K19: =IF(K$1<=$D19,IF(K$1=$D19,K$8+K$11,K$8),"") -> #DIV/0! | L19: =IF(L$1<=$D19,IF(L$1=$D19,L$8+L$11,L$8),"") -> #DIV/0! | M19: =IF(M$1<=$D19,IF(M$1=$D19,M$8+M$11,M$8),"") -> #DIV/0! | N19: =IF(N$1<=$D19,IF(N$1=$D19,N$8+N$11,N$8),"") -> #DIV/0! | ... DV19: =IF(DV$1<=$D19,IF(DV$1=$D19,DV$8+DV$11,DV$8),"")
D20: 36 | E20: 3y IRR Stream | F20: =-$F$6 -> 956250 | G20: =IF(G$1<=$D20,IF(G$1=$D20,G$8+G$11,G$8),"") -> #DIV/0! | H20: =IF(H$1<=$D20,IF(H$1=$D20,H$8+H$11,H$8),"") -> #DIV/0! | I20: =IF(I$1<=$D20,IF(I$1=$D20,I$8+I$11,I$8),"") -> #DIV/0! | J20: =IF(J$1<=$D20,IF(J$1=$D20,J$8+J$11,J$8),"") -> #DIV/0! | K20: =IF(K$1<=$D20,IF(K$1=$D20,K$8+K$11,K$8),"") -> #DIV/0! | L20: =IF(L$1<=$D20,IF(L$1=$D20,L$8+L$11,L$8),"") -> #DIV/0! | M20: =IF(M$1<=$D20,IF(M$1=$D20,M$8+M$11,M$8),"") -> #DIV/0! | N20: =IF(N$1<=$D20,IF(N$1=$D20,N$8+N$11,N$8),"") -> #DIV/0! | ... DV20: =IF(DV$1<=$D20,IF(DV$1=$D20,DV$8+DV$11,DV$8),"")
D21: 60 | E21: 5y IRR Stream | F21: =-$F$6 -> 956250 | G21: =IF(G$1<=$D21,IF(G$1=$D21,G$8+G$11,G$8),"") -> #DIV/0! | H21: =IF(H$1<=$D21,IF(H$1=$D21,H$8+H$11,H$8),"") -> #DIV/0! | I21: =IF(I$1<=$D21,IF(I$1=$D21,I$8+I$11,I$8),"") -> #DIV/0! | J21: =IF(J$1<=$D21,IF(J$1=$D21,J$8+J$11,J$8),"") -> #DIV/0! | K21: =IF(K$1<=$D21,IF(K$1=$D21,K$8+K$11,K$8),"") -> #DIV/0! | L21: =IF(L$1<=$D21,IF(L$1=$D21,L$8+L$11,L$8),"") -> #DIV/0! | M21: =IF(M$1<=$D21,IF(M$1=$D21,M$8+M$11,M$8),"") -> #DIV/0! | N21: =IF(N$1<=$D21,IF(N$1=$D21,N$8+N$11,N$8),"") -> #DIV/0! | ... DV21: =IF(DV$1<=$D21,IF(DV$1=$D21,DV$8+DV$11,DV$8),"")
D22: 84 | E22: 7y IRR Stream | F22: =-$F$6 -> 956250 | G22: =IF(G$1<=$D22,IF(G$1=$D22,G$8+G$11,G$8),"") -> #DIV/0! | H22: =IF(H$1<=$D22,IF(H$1=$D22,H$8+H$11,H$8),"") -> #DIV/0! | I22: =IF(I$1<=$D22,IF(I$1=$D22,I$8+I$11,I$8),"") -> #DIV/0! | J22: =IF(J$1<=$D22,IF(J$1=$D22,J$8+J$11,J$8),"") -> #DIV/0! | K22: =IF(K$1<=$D22,IF(K$1=$D22,K$8+K$11,K$8),"") -> #DIV/0! | L22: =IF(L$1<=$D22,IF(L$1=$D22,L$8+L$11,L$8),"") -> #DIV/0! | M22: =IF(M$1<=$D22,IF(M$1=$D22,M$8+M$11,M$8),"") -> #DIV/0! | N22: =IF(N$1<=$D22,IF(N$1=$D22,N$8+N$11,N$8),"") -> #DIV/0! | ... DV22: =IF(DV$1<=$D22,IF(DV$1=$D22,DV$8+DV$11,DV$8),"")
D23: 120 | E23: 10y IRR Stream | F23: =-$F$6 -> 956250 | G23: =IF(G$1<=$D23,IF(G$1=$D23,G$8+G$11,G$8),"") -> #DIV/0! | H23: =IF(H$1<=$D23,IF(H$1=$D23,H$8+H$11,H$8),"") -> #DIV/0! | I23: =IF(I$1<=$D23,IF(I$1=$D23,I$8+I$11,I$8),"") -> #DIV/0! | J23: =IF(J$1<=$D23,IF(J$1=$D23,J$8+J$11,J$8),"") -> #DIV/0! | K23: =IF(K$1<=$D23,IF(K$1=$D23,K$8+K$11,K$8),"") -> #DIV/0! | L23: =IF(L$1<=$D23,IF(L$1=$D23,L$8+L$11,L$8),"") -> #DIV/0! | M23: =IF(M$1<=$D23,IF(M$1=$D23,M$8+M$11,M$8),"") -> #DIV/0! | N23: =IF(N$1<=$D23,IF(N$1=$D23,N$8+N$11,N$8),"") -> #DIV/0! | ... DV23: =IF(DV$1<=$D23,IF(DV$1=$D23,DV$8+DV$11,DV$8),"") -> #DIV/0!
